cloud_dns/__init__.py
cloud_dns/config.py
cloud_dns/entry_points.py
cloud_dns/project.py
cloud_dns/version.py
cloud_dns-0.3.2.dist-info/DESCRIPTION.rst
cloud_dns-0.3.2.dist-info/METADATA
cloud_dns-0.3.2.dist-info/RECORD
cloud_dns-0.3.2.dist-info/WHEEL
cloud_dns-0.3.2.dist-info/entry_points.txt
cloud_dns-0.3.2.dist-info/metadata.json
cloud_dns-0.3.2.dist-info/pbr.json
cloud_dns-0.3.2.dist-info/top_level.txt
